Codexify/__init__.py
Codexify/converter.py
codexify-0.1.0.dist-info/METADATA
codexify-0.1.0.dist-info/WHEEL
codexify-0.1.0.dist-info/top_level.txt
codexify-0.1.0.dist-info/RECORD
