Metadata-Version: 2.4
Name: Codexify
Version: 0.1.0
Summary: Text-to-coded transformation library
Author: maksalmaz
Author-email: maksalmaz <maksalmaz15@gmail.com>
License: MIT
Requires-Python: >=3.8
Dynamic: author
Dynamic: requires-python
